decp_scraper/__init__.py
decp_scraper/download.py
decp_scraper/extractionAcheteurs.py
decp_scraper/plateformes.csv
decp_scraper/site_utils.py
decp_scraper-1.0.6.dist-info/LICENSE
decp_scraper-1.0.6.dist-info/METADATA
decp_scraper-1.0.6.dist-info/WHEEL
decp_scraper-1.0.6.dist-info/top_level.txt
decp_scraper-1.0.6.dist-info/RECORD
