Metadata-Version: 2.1
Name: decp-scraper
Version: 1.0.6
Summary: Extract DECP files from few websites easily
Home-page: https://github.com/JLoDoesIt/atexo-decp-scraper
Author: JLoDoesIT
Author-email: jlospam@hotmail.com
License: UNKNOWN
Platform: UNKNOWN
Classifier: Programming Language :: Python :: 3
Classifier: License :: OSI Approved :: MIT License
Classifier: Operating System :: OS Independent
Requires-Python: >=3.6
